iggcli/__init__.py
iggcli/__main__.py
iggcli/calls/__init__.py
iggcli/calls/credits.py
iggcli/calls/search.py
iggcli/cli.py
iggcli/core/__init__.py
iggcli/core/scrap.py
iggcli/main.py
iggcli/values/__init__.py
iggcli/values/search.py
iggcli/values/web.py
iggcli-0.1.1.dist-info/METADATA
iggcli-0.1.1.dist-info/WHEEL
iggcli-0.1.1.dist-info/entry_points.txt
iggcli-0.1.1.dist-info/RECORD
