Metadata-Version: 2.1
Name: iggcli
Version: 0.1.1
Summary: Download your games from Igg Games more easily.
License: Beerware
Author: Alekyo4
Author-email: alexsandergomes4742@gmail.com
Requires-Python: >=3.10,<4.0
Classifier: Environment :: Console
Classifier: Intended Audience :: Customer Service
Classifier: License :: Other/Proprietary License
Classifier: Natural Language :: Portuguese (Brazilian)
Classifier: Programming Language :: Python :: 3
Classifier: Programming Language :: Python :: 3.10
Classifier: Programming Language :: Python :: 3.11
Classifier: Topic :: Games/Entertainment
Requires-Dist: beautifulsoup4 (>=4.12.0,<5.0.0)
Requires-Dist: python-slugify (>=8.0.1,<9.0.0)
Requires-Dist: requests (>=2.28.2,<3.0.0)
Requires-Dist: rich (>=13.3.2,<14.0.0)
Requires-Dist: typer (>=0.7.0,<0.8.0)
Project-URL: bug, https://github.com/alekyo4/iggcli/issues
Project-URL: code, https://github.com/alekyo4/iggcli
Project-URL: documentation, https://github.com/alekyo4/iggcli
